socketlib/__init__.py
socketlib/__main__.py
socketlib/basic/__init__.py
socketlib/basic/buffer.py
socketlib/basic/queues.py
socketlib/basic/receive.py
socketlib/basic/send.py
socketlib/cli/__init__.py
socketlib/cli/cli.py
socketlib/client/__init__.py
socketlib/client/client.py
socketlib/exceptions/__init__.py
socketlib/exceptions/exceptions.py
socketlib/server/__init__.py
socketlib/server/server.py
socketlib/services/__init__.py
socketlib/services/abstract_service.py
socketlib/services/samples.py
socketlib/utils/__init__.py
socketlib/utils/logger.py
socketlib/utils/watch_dog.py
pysocklib-0.6.1.dist-info/LICENSE
pysocklib-0.6.1.dist-info/METADATA
pysocklib-0.6.1.dist-info/WHEEL
pysocklib-0.6.1.dist-info/entry_points.txt
pysocklib-0.6.1.dist-info/top_level.txt
pysocklib-0.6.1.dist-info/RECORD
