Metadata-Version: 2.1
Name: pysocklib
Version: 0.6.1
Summary: Library to work with socket clients and servers.
Author-email: Daniel Ibarrola <daniel.ibarrola.sanchez@gmail.com>
License: MIT License
Project-URL: Homepage, https://github.com/Daniel-Ibarrola/SocketLib.git
Keywords: socket,client,server
Classifier: License :: OSI Approved :: MIT License
Classifier: Programming Language :: Python
Classifier: Programming Language :: Python :: 3
Requires-Python: >=3.11
License-File: LICENSE
Provides-Extra: dev
Requires-Dist: build ; extra == 'dev'
Requires-Dist: bumpver ; extra == 'dev'
Requires-Dist: pytest ; extra == 'dev'
Requires-Dist: pytest-mock ; extra == 'dev'
